handyobj/__init__.py
handyobj/object_dict.py
handyobj/smart_list.py
handyobj-0.2.0.dist-info/LICENSE
handyobj-0.2.0.dist-info/METADATA
handyobj-0.2.0.dist-info/WHEEL
handyobj-0.2.0.dist-info/top_level.txt
handyobj-0.2.0.dist-info/RECORD
