Metadata-Version: 2.2
Name: handyobj
Version: 0.2.0
Summary: Add your description here
Author-email: SENHAJI RHAZI Hamza <hamza.senhajirhazi@gmail.com>
Requires-Python: >=3.10
License-File: LICENSE
Requires-Dist: unsync>=1.4.0
